quick_stock/__init__.py
quick_stock/trade_concept_client.py
quick_stock/trade_date_client.py
quick_stock/trade_fund_client.py
quick_stock/trade_index_client.py
quick_stock/trade_stock_client.py
quick_stock/d/__init__.py
quick_stock/d/d.py
quick_stock/remote/__init__.py
quick_stock/remote/date.py
quick_stock/remote/fund.py
quick_stock/remote/index.py
quick_stock/remote/req.py
quick_stock/remote/stock.py
quick_stock/remote/tonghuashun.py
quick_stock/share/__init__.py
quick_stock/share/share.py
quick_stock_sdk-0.1.7.dist-info/METADATA
quick_stock_sdk-0.1.7.dist-info/WHEEL
quick_stock_sdk-0.1.7.dist-info/top_level.txt
quick_stock_sdk-0.1.7.dist-info/RECORD
